{
    "appointments": {
        "repository": {
            "name": "appmaker-appointments",
            "branch": "dev",
            "host": {
                "git": "https:\/\/github.com\/LouisOuellet\/",
                "raw": "https:\/\/raw.githubusercontent.com\/LouisOuellet\/"
            },
            "manifest": "\/dist\/data\/manifest.json",
            "branches": [
                "main",
                "beta",
                "dev"
            ],
            "table": [
              "appointments"
            ]
        }
    },
    "automatons": {
        "repository": {
            "name": "appmaker-automatons",
            "branch": "dev",
            "host": {
                "git": "https:\/\/github.com\/LouisOuellet\/",
                "raw": "https:\/\/raw.githubusercontent.com\/LouisOuellet\/"
            },
            "manifest": "\/dist\/data\/manifest.json",
            "branches": [
                "main",
                "beta",
                "dev"
            ]
        }
    },
    "callbacks": {
        "repository": {
            "name": "appmaker-callbacks",
            "branch": "dev",
            "host": {
                "git": "https:\/\/github.com\/LouisOuellet\/",
                "raw": "https:\/\/raw.githubusercontent.com\/LouisOuellet\/"
            },
            "manifest": "\/dist\/data\/manifest.json",
            "branches": [
                "main",
                "beta",
                "dev"
            ]
        }
    },
    "calls": {
        "repository": {
            "name": "appmaker-calls",
            "branch": "dev",
            "host": {
                "git": "https:\/\/github.com\/LouisOuellet\/",
                "raw": "https:\/\/raw.githubusercontent.com\/LouisOuellet\/"
            },
            "manifest": "\/dist\/data\/manifest.json",
            "branches": [
                "main",
                "beta",
                "dev"
            ],
            "table": [
              "calls"
            ]
        }
    },
    "categories": {
        "repository": {
            "name": "appmaker-categories",
            "branch": "dev",
            "host": {
                "git": "https:\/\/github.com\/LouisOuellet\/",
                "raw": "https:\/\/raw.githubusercontent.com\/LouisOuellet\/"
            },
            "manifest": "\/dist\/data\/manifest.json",
            "branches": [
                "main",
                "beta",
                "dev"
            ]
        }
    },
    "clients": {
        "repository": {
            "name": "appmaker-clients",
            "branch": "dev",
            "host": {
                "git": "https:\/\/github.com\/LouisOuellet\/",
                "raw": "https:\/\/raw.githubusercontent.com\/LouisOuellet\/"
            },
            "manifest": "\/dist\/data\/manifest.json",
            "branches": [
                "main",
                "beta",
                "dev"
            ]
        }
    },
    "comments": {
        "repository": {
            "name": "appmaker-comments",
            "branch": "dev",
            "host": {
                "git": "https:\/\/github.com\/LouisOuellet\/",
                "raw": "https:\/\/raw.githubusercontent.com\/LouisOuellet\/"
            },
            "manifest": "\/dist\/data\/manifest.json",
            "branches": [
                "main",
                "beta",
                "dev"
            ],
            "table": [
              "comments"
            ]
        }
    },
    "contacts": {
        "repository": {
            "name": "appmaker-contacts",
            "branch": "dev",
            "host": {
                "git": "https:\/\/github.com\/LouisOuellet\/",
                "raw": "https:\/\/raw.githubusercontent.com\/LouisOuellet\/"
            },
            "manifest": "\/dist\/data\/manifest.json",
            "branches": [
                "main",
                "beta",
                "dev"
            ]
        }
    },
    "containers": {
        "repository": {
            "name": "appmaker-containers",
            "branch": "dev",
            "host": {
                "git": "https:\/\/github.com\/LouisOuellet\/",
                "raw": "https:\/\/raw.githubusercontent.com\/LouisOuellet\/"
            },
            "manifest": "\/dist\/data\/manifest.json",
            "branches": [
                "main",
                "beta",
                "dev"
            ],
            "table": [
              "containers"
            ]
        }
    },
    "conversations": {
        "repository": {
            "name": "appmaker-conversations",
            "branch": "dev",
            "host": {
                "git": "https:\/\/github.com\/LouisOuellet\/",
                "raw": "https:\/\/raw.githubusercontent.com\/LouisOuellet\/"
            },
            "manifest": "\/dist\/data\/manifest.json",
            "branches": [
                "main",
                "beta",
                "dev"
            ],
            "table": [
              "conversations"
            ]
        }
    },
    "dashboard": {
        "repository": {
            "name": "appmaker-dashboard",
            "branch": "dev",
            "host": {
                "git": "https:\/\/github.com\/LouisOuellet\/",
                "raw": "https:\/\/raw.githubusercontent.com\/LouisOuellet\/"
            },
            "manifest": "\/dist\/data\/manifest.json",
            "branches": [
                "main",
                "beta",
                "dev"
            ],
            "table": [
              "dashboard"
            ]
        }
    },
    "debug": {
        "repository": {
            "name": "appmaker-debug",
            "branch": "dev",
            "host": {
                "git": "https:\/\/github.com\/LouisOuellet\/",
                "raw": "https:\/\/raw.githubusercontent.com\/LouisOuellet\/"
            },
            "manifest": "\/dist\/data\/manifest.json",
            "branches": [
                "main",
                "beta",
                "dev"
            ]
        }
    },
    "dev": {
        "repository": {
            "name": "appmaker-dev",
            "branch": "dev",
            "host": {
                "git": "https:\/\/github.com\/LouisOuellet\/",
                "raw": "https:\/\/raw.githubusercontent.com\/LouisOuellet\/"
            },
            "manifest": "\/dist\/data\/manifest.json",
            "branches": [
                "main",
                "beta",
                "dev"
            ]
        }
    },
    "dispatch": {
        "repository": {
            "name": "appmaker-dispatch",
            "branch": "dev",
            "host": {
                "git": "https:\/\/github.com\/LouisOuellet\/",
                "raw": "https:\/\/raw.githubusercontent.com\/LouisOuellet\/"
            },
            "manifest": "\/dist\/data\/manifest.json",
            "branches": [
                "main",
                "beta",
                "dev"
            ]
        }
    },
    "groups": {
        "repository": {
            "name": "appmaker-groups",
            "branch": "dev",
            "host": {
                "git": "https:\/\/github.com\/LouisOuellet\/",
                "raw": "https:\/\/raw.githubusercontent.com\/LouisOuellet\/"
            },
            "manifest": "\/dist\/data\/manifest.json",
            "branches": [
                "main",
                "beta",
                "dev"
            ]
        }
    },
    "issues": {
        "repository": {
            "name": "appmaker-issues",
            "branch": "dev",
            "host": {
                "git": "https:\/\/github.com\/LouisOuellet\/",
                "raw": "https:\/\/raw.githubusercontent.com\/LouisOuellet\/"
            },
            "manifest": "\/dist\/data\/manifest.json",
            "branches": [
                "main",
                "beta",
                "dev"
            ],
            "table": [
              "issues"
            ]
        }
    },
    "leads": {
        "repository": {
            "name": "appmaker-leads",
            "branch": "dev",
            "host": {
                "git": "https:\/\/github.com\/LouisOuellet\/",
                "raw": "https:\/\/raw.githubusercontent.com\/LouisOuellet\/"
            },
            "manifest": "\/dist\/data\/manifest.json",
            "branches": [
                "main",
                "beta",
                "dev"
            ]
        }
    },
    "lsp": {
        "repository": {
            "name": "appmaker-lsp",
            "branch": "dev",
            "host": {
                "git": "https:\/\/github.com\/LouisOuellet\/",
                "raw": "https:\/\/raw.githubusercontent.com\/LouisOuellet\/"
            },
            "manifest": "\/dist\/data\/manifest.json",
            "branches": [
                "main",
                "beta",
                "dev"
            ]
        }
    },
    "messages": {
        "repository": {
            "name": "appmaker-messages",
            "branch": "dev",
            "host": {
                "git": "https:\/\/github.com\/LouisOuellet\/",
                "raw": "https:\/\/raw.githubusercontent.com\/LouisOuellet\/"
            },
            "manifest": "\/dist\/data\/manifest.json",
            "branches": [
                "main",
                "beta",
                "dev"
            ],
            "table": [
              "messages"
            ]
        }
    },
    "my_clients": {
        "repository": {
            "name": "appmaker-my_clients",
            "branch": "dev",
            "host": {
                "git": "https:\/\/github.com\/LouisOuellet\/",
                "raw": "https:\/\/raw.githubusercontent.com\/LouisOuellet\/"
            },
            "manifest": "\/dist\/data\/manifest.json",
            "branches": [
                "main",
                "beta",
                "dev"
            ]
        }
    },
    "my_containers": {
        "repository": {
            "name": "appmaker-my_containers",
            "branch": "dev",
            "host": {
                "git": "https:\/\/github.com\/LouisOuellet\/",
                "raw": "https:\/\/raw.githubusercontent.com\/LouisOuellet\/"
            },
            "manifest": "\/dist\/data\/manifest.json",
            "branches": [
                "main",
                "beta",
                "dev"
            ]
        }
    },
    "my_leads": {
        "repository": {
            "name": "appmaker-my_leads",
            "branch": "dev",
            "host": {
                "git": "https:\/\/github.com\/LouisOuellet\/",
                "raw": "https:\/\/raw.githubusercontent.com\/LouisOuellet\/"
            },
            "manifest": "\/dist\/data\/manifest.json",
            "branches": [
                "main",
                "beta",
                "dev"
            ]
        }
    },
    "my_prospects": {
        "repository": {
            "name": "appmaker-my_prospects",
            "branch": "dev",
            "host": {
                "git": "https:\/\/github.com\/LouisOuellet\/",
                "raw": "https:\/\/raw.githubusercontent.com\/LouisOuellet\/"
            },
            "manifest": "\/dist\/data\/manifest.json",
            "branches": [
                "main",
                "beta",
                "dev"
            ]
        }
    },
    "my_tickets": {
        "repository": {
            "name": "appmaker-my_tickets",
            "branch": "dev",
            "host": {
                "git": "https:\/\/github.com\/LouisOuellet\/",
                "raw": "https:\/\/raw.githubusercontent.com\/LouisOuellet\/"
            },
            "manifest": "\/dist\/data\/manifest.json",
            "branches": [
                "main",
                "beta",
                "dev"
            ]
        }
    },
    "notes": {
        "repository": {
            "name": "appmaker-notes",
            "branch": "dev",
            "host": {
                "git": "https:\/\/github.com\/LouisOuellet\/",
                "raw": "https:\/\/raw.githubusercontent.com\/LouisOuellet\/"
            },
            "manifest": "\/dist\/data\/manifest.json",
            "branches": [
                "main",
                "beta",
                "dev"
            ],
            "table": [
              "notes"
            ]
        }
    },
    "organizations": {
        "repository": {
            "name": "appmaker-organizations",
            "branch": "dev",
            "host": {
                "git": "https:\/\/github.com\/LouisOuellet\/",
                "raw": "https:\/\/raw.githubusercontent.com\/LouisOuellet\/"
            },
            "manifest": "\/dist\/data\/manifest.json",
            "branches": [
                "main",
                "beta",
                "dev"
            ],
            "table": [
              "organizations"
            ]
        }
    },
    "permissions": {
        "repository": {
            "name": "appmaker-permissions",
            "branch": "dev",
            "host": {
                "git": "https:\/\/github.com\/LouisOuellet\/",
                "raw": "https:\/\/raw.githubusercontent.com\/LouisOuellet\/"
            },
            "manifest": "\/dist\/data\/manifest.json",
            "branches": [
                "main",
                "beta",
                "dev"
            ]
        }
    },
    "plugins": {
        "repository": {
            "name": "appmaker-plugins",
            "branch": "dev",
            "host": {
                "git": "https:\/\/github.com\/LouisOuellet\/",
                "raw": "https:\/\/raw.githubusercontent.com\/LouisOuellet\/"
            },
            "manifest": "\/dist\/data\/manifest.json",
            "branches": [
                "main",
                "beta",
                "dev"
            ]
        }
    },
    "profile": {
        "repository": {
            "name": "appmaker-profile",
            "branch": "dev",
            "host": {
                "git": "https:\/\/github.com\/LouisOuellet\/",
                "raw": "https:\/\/raw.githubusercontent.com\/LouisOuellet\/"
            },
            "manifest": "\/dist\/data\/manifest.json",
            "branches": [
                "main",
                "beta",
                "dev"
            ]
        }
    },
    "roles": {
        "repository": {
            "name": "appmaker-roles",
            "branch": "dev",
            "host": {
                "git": "https:\/\/github.com\/LouisOuellet\/",
                "raw": "https:\/\/raw.githubusercontent.com\/LouisOuellet\/"
            },
            "manifest": "\/dist\/data\/manifest.json",
            "branches": [
                "main",
                "beta",
                "dev"
            ]
        }
    },
    "sales_genie": {
        "repository": {
            "name": "appmaker-sales_genie",
            "branch": "dev",
            "host": {
                "git": "https:\/\/github.com\/LouisOuellet\/",
                "raw": "https:\/\/raw.githubusercontent.com\/LouisOuellet\/"
            },
            "manifest": "\/dist\/data\/manifest.json",
            "branches": [
                "main",
                "beta",
                "dev"
            ]
        }
    },
    "search": {
        "repository": {
            "name": "appmaker-search",
            "branch": "dev",
            "host": {
                "git": "https:\/\/github.com\/LouisOuellet\/",
                "raw": "https:\/\/raw.githubusercontent.com\/LouisOuellet\/"
            },
            "manifest": "\/dist\/data\/manifest.json",
            "branches": [
                "main",
                "beta",
                "dev"
            ]
        }
    },
    "services": {
        "repository": {
            "name": "appmaker-services",
            "branch": "dev",
            "host": {
                "git": "https:\/\/github.com\/LouisOuellet\/",
                "raw": "https:\/\/raw.githubusercontent.com\/LouisOuellet\/"
            },
            "manifest": "\/dist\/data\/manifest.json",
            "branches": [
                "main",
                "beta",
                "dev"
            ],
            "table": [
              "services"
            ]
        }
    },
    "settings": {
        "repository": {
            "name": "appmaker-settings",
            "branch": "dev",
            "host": {
                "git": "https:\/\/github.com\/LouisOuellet\/",
                "raw": "https:\/\/raw.githubusercontent.com\/LouisOuellet\/"
            },
            "manifest": "\/dist\/data\/manifest.json",
            "branches": [
                "main",
                "beta",
                "dev"
            ]
        }
    },
    "statuses": {
        "repository": {
            "name": "appmaker-statuses",
            "branch": "dev",
            "host": {
                "git": "https:\/\/github.com\/LouisOuellet\/",
                "raw": "https:\/\/raw.githubusercontent.com\/LouisOuellet\/"
            },
            "manifest": "\/dist\/data\/manifest.json",
            "branches": [
                "main",
                "beta",
                "dev"
            ]
        }
    },
    "sub_categories": {
        "repository": {
            "name": "appmaker-sub_categories",
            "branch": "dev",
            "host": {
                "git": "https:\/\/github.com\/LouisOuellet\/",
                "raw": "https:\/\/raw.githubusercontent.com\/LouisOuellet\/"
            },
            "manifest": "\/dist\/data\/manifest.json",
            "branches": [
                "main",
                "beta",
                "dev"
            ]
        }
    },
    "tags": {
        "repository": {
            "name": "appmaker-tags",
            "branch": "dev",
            "host": {
                "git": "https:\/\/github.com\/LouisOuellet\/",
                "raw": "https:\/\/raw.githubusercontent.com\/LouisOuellet\/"
            },
            "manifest": "\/dist\/data\/manifest.json",
            "branches": [
                "main",
                "beta",
                "dev"
            ],
            "table": [
              "tags"
            ]
        }
    },
    "tickets": {
        "repository": {
            "name": "appmaker-tickets",
            "branch": "dev",
            "host": {
                "git": "https:\/\/github.com\/LouisOuellet\/",
                "raw": "https:\/\/raw.githubusercontent.com\/LouisOuellet\/"
            },
            "manifest": "\/dist\/data\/manifest.json",
            "branches": [
                "main",
                "beta",
                "dev"
            ],
            "table": [
              "tickets"
            ]
        }
    },
    "users": {
        "repository": {
            "name": "appmaker-users",
            "branch": "dev",
            "host": {
                "git": "https:\/\/github.com\/LouisOuellet\/",
                "raw": "https:\/\/raw.githubusercontent.com\/LouisOuellet\/"
            },
            "manifest": "\/dist\/data\/manifest.json",
            "branches": [
                "main",
                "beta",
                "dev"
            ]
        }
    }
}
